tooly/.gitignore
tooly/__init__.py
tooly/args.py
tooly/checker.py
tooly/files.py
tooly/logs.py
tooly/parser.py
tooly/sh.py
tooly/sqliteDb.py
tooly/thread.py
tooly/types.py
tooly-0.1.58.dist-info/METADATA
tooly-0.1.58.dist-info/WHEEL
tooly-0.1.58.dist-info/RECORD
