Metadata-Version: 2.1
Name: tooly
Version: 0.1.58
Summary: 
Author: 方块八
Author-email: liyuan5202004@qq.com
Requires-Python: >=3.6,<4.0
Classifier: Programming Language :: Python :: 3
Classifier: Programming Language :: Python :: 3.6
Classifier: Programming Language :: Python :: 3.7
Classifier: Programming Language :: Python :: 3.8
Classifier: Programming Language :: Python :: 3.9
Classifier: Programming Language :: Python :: 3.10
Classifier: Programming Language :: Python :: 3.11
Classifier: Programming Language :: Python :: 3.12
Classifier: Programming Language :: Python :: 3.13
Requires-Dist: argcomplete (>=3.0.0)
Requires-Dist: pymysql (>=1.0.0)
